miesc/__init__.py
miesc/__main__.py
miesc/mcp_server.py
miesc/adapters/__init__.py
miesc/agents/__init__.py
miesc/api/__init__.py
miesc/api/rest.py
miesc/cli/__init__.py
miesc/cli/main.py
miesc/core/__init__.py
miesc/core/orchestrator.py
miesc/core/quick_scanner.py
miesc/detectors/__init__.py
miesc/detectors/examples.py
miesc/llm/__init__.py
miesc/mcp/__init__.py
miesc/ml/__init__.py
miesc/plugins/__init__.py
miesc/plugins/config.py
miesc/plugins/manager.py
miesc/plugins/templates/__init__.py
miesc/security/__init__.py
miesc-5.0.1.dist-info/licenses/LICENSE
src/__init__.py
src/miesc_core.py
src/miesc_policy_mapper.py
src/miesc_risk_engine.py
src/adapters/__init__.py
src/adapters/aderyn_adapter.py
src/adapters/advanced_detector_adapter.py
src/adapters/algorand_adapter.py
src/adapters/audit_consensus_adapter.py
src/adapters/bridge_monitor_adapter.py
src/adapters/cardano_adapter.py
src/adapters/certora_adapter.py
src/adapters/circom_analyzer_adapter.py
src/adapters/contract_clone_detector_adapter.py
src/adapters/crosschain_adapter.py
src/adapters/dagnn_adapter.py
src/adapters/defi_adapter.py
src/adapters/dogefuzz_adapter.py
src/adapters/echidna_adapter.py
src/adapters/exploit_synthesizer_adapter.py
src/adapters/foundry_adapter.py
src/adapters/fouranalyzer_adapter.py
src/adapters/gas_analyzer_adapter.py
src/adapters/gptlens_adapter.py
src/adapters/gptscan_adapter.py
src/adapters/halmos_adapter.py
src/adapters/hardhat_adapter.py
src/adapters/iaudit_adapter.py
src/adapters/invariant_synthesizer.py
src/adapters/l2_validator_adapter.py
src/adapters/llamaaudit_adapter.py
src/adapters/llmbugscanner_adapter.py
src/adapters/llmsmartaudit_adapter.py
src/adapters/manticore_adapter.py
src/adapters/medusa_adapter.py
src/adapters/mev_detector_adapter.py
src/adapters/move_adapter.py
src/adapters/mythril_adapter.py
src/adapters/near_adapter.py
src/adapters/oyente_adapter.py
src/adapters/pakala_adapter.py
src/adapters/peculiar_adapter.py
src/adapters/propertygpt_adapter.py
src/adapters/remediation_validator_adapter.py
miesc-5.0.1.dist-info/METADATA
miesc-5.0.1.dist-info/WHEEL
miesc-5.0.1.dist-info/entry_points.txt
miesc-5.0.1.dist-info/top_level.txt
miesc-5.0.1.dist-info/RECORD
