Metadata-Version: 2.4
Name: miesc
Version: 5.0.1
Summary: Multi-layer Intelligent Evaluation for Smart Contracts - AI-enhanced MCP-compatible blockchain security framework
Author-email: Fernando Boiero <fboiero@frvm.utn.edu.ar>
License-Expression: AGPL-3.0-only
Project-URL: Homepage, https://github.com/fboiero/MIESC
Project-URL: Documentation, https://fboiero.github.io/MIESC
Project-URL: Repository, https://github.com/fboiero/MIESC.git
Project-URL: Bug Tracker, https://github.com/fboiero/MIESC/issues
Keywords: blockchain,ethereum,smart-contracts,security,static-analysis,formal-verification,vulnerability-detection,mcp,model-context-protocol
Classifier: Development Status :: 4 - Beta
Classifier: Intended Audience :: Developers
Classifier: Intended Audience :: Science/Research
Classifier: Topic :: Security
Classifier: Topic :: Software Development :: Quality Assurance
Classifier: Programming Language :: Python :: 3
Classifier: Programming Language :: Python :: 3.12
Classifier: Programming Language :: Python :: 3.13
Classifier: Programming Language :: Python :: 3.14
Classifier: Operating System :: OS Independent
Requires-Python: >=3.12
License-File: LICENSE
Requires-Dist: click>=8.1.0
Requires-Dist: pydantic>=2.0.0
Requires-Dist: pyyaml>=6.0.0
Requires-Dist: jinja2>=3.1.0
Requires-Dist: slither-analyzer>=0.10.0
Provides-Extra: dev
Requires-Dist: pytest>=7.0.0; extra == "dev"
Requires-Dist: pytest-cov>=4.0.0; extra == "dev"
Requires-Dist: black>=23.0.0; extra == "dev"
Requires-Dist: ruff>=0.1.0; extra == "dev"
Requires-Dist: mypy>=1.0.0; extra == "dev"
Provides-Extra: symbolic
Requires-Dist: mythril>=0.24.0; extra == "symbolic"
Provides-Extra: web3
Requires-Dist: web3>=6.0.0; extra == "web3"
Provides-Extra: docs
Requires-Dist: mkdocs>=1.5.0; extra == "docs"
Requires-Dist: mkdocs-material>=9.0.0; extra == "docs"
Provides-Extra: metrics
Requires-Dist: prometheus-client>=0.19.0; extra == "metrics"
Provides-Extra: cli
Requires-Dist: rich>=13.0.0; extra == "cli"
Provides-Extra: watch
Requires-Dist: watchdog>=3.0.0; extra == "watch"
Provides-Extra: mcp
Requires-Dist: mcp[cli]>=1.0.0; extra == "mcp"
Provides-Extra: pdf
Requires-Dist: weasyprint>=60.0; extra == "pdf"
Requires-Dist: markdown>=3.5.0; extra == "pdf"
Provides-Extra: llm
Requires-Dist: openai>=1.0.0; extra == "llm"
Requires-Dist: anthropic>=0.18.0; extra == "llm"
Requires-Dist: httpx>=0.25.0; extra == "llm"
Provides-Extra: web
Requires-Dist: fastapi>=0.104.0; extra == "web"
Requires-Dist: uvicorn>=0.24.0; extra == "web"
Requires-Dist: flask>=3.0.0; extra == "web"
Requires-Dist: flask-socketio>=5.3.0; extra == "web"
Requires-Dist: flask-cors>=4.0.0; extra == "web"
Requires-Dist: streamlit>=1.28.0; extra == "web"
Requires-Dist: plotly>=5.18.0; extra == "web"
Provides-Extra: django
Requires-Dist: django>=5.0.0; extra == "django"
Requires-Dist: djangorestframework>=3.14.0; extra == "django"
Requires-Dist: django-cors-headers>=4.3.0; extra == "django"
Provides-Extra: full
Requires-Dist: rich>=13.0.0; extra == "full"
Requires-Dist: prometheus-client>=0.19.0; extra == "full"
Requires-Dist: openai>=1.0.0; extra == "full"
Requires-Dist: anthropic>=0.18.0; extra == "full"
Requires-Dist: httpx>=0.25.0; extra == "full"
Requires-Dist: fastapi>=0.104.0; extra == "full"
Requires-Dist: uvicorn>=0.24.0; extra == "full"
Requires-Dist: flask>=3.0.0; extra == "full"
Requires-Dist: flask-socketio>=5.3.0; extra == "full"
Requires-Dist: flask-cors>=4.0.0; extra == "full"
Requires-Dist: streamlit>=1.28.0; extra == "full"
Requires-Dist: plotly>=5.18.0; extra == "full"
Requires-Dist: weasyprint>=60.0; extra == "full"
Requires-Dist: markdown>=3.5.0; extra == "full"
Dynamic: license-file
